{"data":{"markdownRemark":{"html":"<p>Lorem ipsum dolor sit amet consectetur adipisicing elit. Perspiciatis quo voluptates repudiandae aperiam ducimus veniam pariatur incidunt, numquam corporis soluta nobis itaque nam voluptas repellendus voluptatum animi esse amet eius. Lorem ipsum dolor sit amet consectetur adipisicing elit. Perspiciatis quo voluptates repudiandae aperiam ducimus veniam pariatur incidunt, numquam corporis soluta nobis itaque nam voluptas repellendus voluptatum animi esse amet eius. Lorem ipsum dolor sit amet consectetur adipisicing elit. Perspiciatis quo voluptates repudiandae aperiam ducimus veniam pariatur incidunt, numquam corporis soluta nobis itaque nam voluptas repellendus voluptatum animi esse amet eius. Lorem ipsum dolor sit amet consectetur adipisicing elit. Perspiciatis quo voluptates repudiandae aperiam ducimus veniam pariatur incidunt, numquam corporis soluta nobis itaque nam voluptas repellendus voluptatum animi esse amet eius. Lorem ipsum dolor sit amet consectetur adipisicing elit. Perspiciatis quo voluptates repudiandae aperiam ducimus veniam pariatur incidunt, numquam corporis soluta nobis itaque nam voluptas repellendus voluptatum animi esse amet eius. Lorem ipsum dolor sit amet consectetur adipisicing elit. Perspiciatis quo voluptates repudiandae aperiam ducimus veniam pariatur incidunt, numquam corporis soluta nobis itaque nam voluptas repellendus voluptatum animi esse amet eius. Lorem ipsum dolor sit amet consectetur adipisicing elit. Perspiciatis quo voluptates repudiandae aperiam ducimus veniam pariatur incidunt, numquam corporis soluta nobis itaque nam voluptas repellendus voluptatum animi esse amet eius. Lorem ipsum dolor sit amet consectetur adipisicing elit. Perspiciatis quo voluptates repudiandae aperiam ducimus veniam pariatur incidunt, numquam corporis soluta nobis itaque nam voluptas repellendus voluptatum animi esse amet eius.</p>\n<div><my-component>Davis Example</my-component></div>","frontmatter":{"title":"Davis Theme","date":null}}},"pageContext":{"slug":"/work/davis-theme/"}}